boxtestpy/__init__.py
boxtestpy/plotting.py
boxtestpy/stats.py
boxtestpy-0.2.0.dist-info/licenses/LICENSE
boxtestpy-0.2.0.dist-info/METADATA
boxtestpy-0.2.0.dist-info/WHEEL
boxtestpy-0.2.0.dist-info/top_level.txt
boxtestpy-0.2.0.dist-info/RECORD
