Metadata-Version: 2.4
Name: boxTestpy
Version: 0.2.0
Summary: Beginner-friendly side-by-side boxplots and two-sample tests (t-test / Mann–Whitney).
Author-email: Arkaprabha Sau <arka.doctor@gmail.com>
Maintainer: Arkaprabha Sau, Santanu Phadikar, Ishita Bhakta
License-Expression: MIT
Project-URL: Homepage, https://github.com/arka1985
Project-URL: Repository, https://github.com/arka1985/boxTestpy
Classifier: Development Status :: 5 - Production/Stable
Classifier: Intended Audience :: Science/Research
Classifier: Intended Audience :: Education
Classifier: Operating System :: OS Independent
Classifier: Programming Language :: Python :: 3
Classifier: Topic :: Scientific/Engineering :: Visualization
Classifier: Topic :: Scientific/Engineering :: Information Analysis
Requires-Python: >=3.8
License-File: LICENSE
Requires-Dist: numpy>=1.21
Requires-Dist: pandas>=1.3
Requires-Dist: matplotlib>=3.4
Requires-Dist: scipy>=1.7
Provides-Extra: plotting
Requires-Dist: seaborn>=0.11; extra == "plotting"
Dynamic: license-file
